Metadata-Version: 2.1
Name: BenMixPage
Version: 1.0.3.1
Summary: Python based web automation tool. It can control the browser and send and receive data packets.
Home-page: https://gitee.com/g1879/MixPage
Author: g1879
Author-email: g1879@qq.com
License: BSD
Keywords: MixPage
Classifier: Programming Language :: Python :: 3.6
Classifier: Development Status :: 4 - Beta
Classifier: Topic :: Utilities
Classifier: License :: OSI Approved :: BSD License
Requires-Python: >=3.6
License-File: LICENSE
Requires-Dist: lxml
Requires-Dist: requests
Requires-Dist: cssselect
Requires-Dist: DownloadKit >=0.5.3
Requires-Dist: selenium
Requires-Dist: tldextract
